djangoadminkit/__init__.py
djangoadminkit/apps.py
djangoadminkit/settings.py
djangoadminkit/urls.py
djangoadminkit/static/admin/css/app.css
djangoadminkit/templates/admin/actions.html
djangoadminkit/templates/admin/app_list.html
djangoadminkit/templates/admin/base.html
djangoadminkit/templates/admin/change_form.html
djangoadminkit/templates/admin/change_list.html
djangoadminkit/templates/admin/change_list_object_tools.html
djangoadminkit/templates/admin/change_list_results.html
djangoadminkit/templates/admin/index.html
djangoadminkit/templates/admin/nav_sidebar.html
djangoadminkit/templates/admin/search_form.html
djangoadminkit-0.1.1.dist-info/METADATA
djangoadminkit-0.1.1.dist-info/WHEEL
djangoadminkit-0.1.1.dist-info/top_level.txt
djangoadminkit-0.1.1.dist-info/RECORD
